simple_ip_tools/__init__.py
simple_ip_tools-0.2.1.dist-info/METADATA
simple_ip_tools-0.2.1.dist-info/WHEEL
simple_ip_tools-0.2.1.dist-info/top_level.txt
simple_ip_tools-0.2.1.dist-info/RECORD
