Metadata-Version: 2.4
Name: simple-ip-tools
Version: 0.2.1
Summary: A simple IP address to country mapping tool
Author: Wellbia.com Co.,Ltd.
Author-email: opensource@wellbia.com
Classifier: License :: OSI Approved :: MIT License
Classifier: Programming Language :: Python :: 3.11
Classifier: Programming Language :: Python :: 3.12
Requires-Dist: pytricia
Requires-Dist: ipaddress
Dynamic: author
Dynamic: author-email
Dynamic: classifier
Dynamic: description
Dynamic: description-content-type
Dynamic: requires-dist
Dynamic: summary
